{
  "entity": {
    "entity_type": "VI_THUOC",
    "id": "VT_MAU_DON_BI",
    "ten_raw": "Mẫu đơn bì",
    "ten_khoa_hoc": "$Paeonia suffruticosa Andr. (Paeonia arborea Donn, Paeonia moutan Sims.); Paeonia suffruticosa Andr. (Paeonia moutan Sims)$",
    "ho_thuc_vat": "$Mao lương Ranunculaceae; Hoàng liên Ranunculaceae$",
    "variants": [],
    "properties": {
      "lieu_dung_chung": "Ngày dùng $5-10g$ dưới dạng thuốc sắc; Ngày dùng $6-12g$ dưới dạng thuốc sắc.",
      "muc_do_doc": "Không độc",
      "bo_phan_dung": "vỏ rễ",
      "phan_bo": "Trung Quốc, Việt Nam (Sa Pa, Tam Đảo)",
      "thu_hai": "tháng 8-9",
      "che_bien_tho": "đào lấy rễ, rửa sạch đất cát, cạo bỏ vỏ ngoài, phơi khô",
      "trieu_chung_ngo_doc": "Không có thông tin"
    },
    "display_name": "Vị thuốc Mẫu đơn bì",
    "canonical_name": "Vị thuốc Mẫu đơn bì"
  },
  "nodes": [
    {
      "id": "BT_KHAT_NUOC_DON_BI",
      "label": "BaiThuoc",
      "properties": {
        "canonical_name": "Bài thuốc Khát nước đơn bi",
        "aliases": [
          "khat nuoc don bi",
          "khát nước đơn bi",
          "khatnuocdonbi"
        ],
        "search_vector_hint": "Bài thuốc Khát nước đơn bi thuộc nhóm bài thuốc, thường liên quan đến điều trị khát nước."
      }
    },
    {
      "id": "BT_TRUOC_DE_DON_BI",
      "label": "BaiThuoc",
      "properties": {
        "canonical_name": "Bài thuốc Trước đẻ đơn bi",
        "aliases": [
          "truocdedonbi",
          "truoc de don bi",
          "trước đẻ đơn bi"
        ],
        "search_vector_hint": "Bài thuốc Trước đẻ đơn bi thuộc nhóm bài thuốc, thường liên quan đến phụ nữ trước khi sinh."
      }
    },
    {
      "id": "BT_U_CUC_DON_BI",
      "label": "BaiThuoc",
      "properties": {
        "canonical_name": "Bài thuốc U cục đơn bi",
        "aliases": [
          "u cục đơn bi",
          "ucucdonbi",
          "u cuc don bi"
        ],
        "search_vector_hint": "Bài thuốc U cục đơn bi thuộc nhóm bài thuốc, thường liên quan đến điều trị u cục."
      }
    },
    {
      "id": "B_BE_KINH",
      "label": "Benh",
      "properties": {
        "canonical_name": "Kinh Bế",
        "aliases": [
          "be kinh",
          "bế",
          "be",
          "bế kinh",
          "bekinh"
        ],
        "search_vector_hint": "Kinh Bế thuộc nhóm Bệnh, thường liên quan đến rối loạn kinh nguyệt."
      }
    },
    {
      "id": "B_KINH_NGUYET_KHONG_DEU",
      "label": "Benh",
      "properties": {
        "canonical_name": "Bệnh Kinh nguyệt không đều",
        "aliases": [
          "kinhnguyetthatthuong",
          "kinh nguyet khong deu",
          "roi loan kinh nguyet",
          "kinh nguyệt không đều",
          "kinh nguyet that thuong",
          "kinhnguyetkhongdeu",
          "kinh nguyệt thất thường",
          "roiloankinhnguyet",
          "rối loạn kinh nguyệt"
        ],
        "search_vector_hint": "Bệnh Kinh nguyệt không đều thuộc nhóm bệnh, thường liên quan đến rối loạn nội tiết tố nữ."
      }
    },
    {
      "id": "B_SAU_DE",
      "label": "Benh",
      "properties": {
        "canonical_name": "Bệnh Sau đẻ",
        "aliases": [
          "sau de",
          "sau đẻ",
          "saude",
          "hau san",
          "hausan",
          "hậu sản"
        ],
        "search_vector_hint": "Bệnh Sau đẻ thuộc nhóm bệnh, thường liên quan đến phụ nữ sau khi sinh."
      }
    },
    {
      "id": "B_SOT_NONG",
      "label": "Benh",
      "properties": {
        "canonical_name": "Triệu chứng Sốt nóng",
        "aliases": [
          "sotcao",
          "sotnong",
          "sot nong",
          "sốt cao",
          "sot cao",
          "sốt nóng"
        ],
        "search_vector_hint": "Triệu chứng Sốt nóng thuộc nhóm Triệu chứng, thường liên quan đến phản ứng của cơ thể với nhiễm trùng."
      }
    },
    {
      "id": "B_TRUOC_DE",
      "label": "Benh",
      "properties": {
        "canonical_name": "Bệnh Trước đẻ",
        "aliases": [
          "truocde",
          "truoc de",
          "trước đẻ"
        ],
        "search_vector_hint": "Bệnh Trước đẻ thuộc nhóm bệnh, thường liên quan đến phụ nữ trước khi sinh."
      }
    },
    {
      "id": "B_U_CUC",
      "label": "Benh",
      "properties": {
        "canonical_name": "Bệnh U cục",
        "aliases": [
          "khoiu",
          "u cuc",
          "khoi u",
          "u cục",
          "u buou",
          "ucuc",
          "u bướu",
          "khối u",
          "ubuou"
        ],
        "search_vector_hint": "Bệnh U cục thuộc nhóm Bệnh, thường liên quan đến sự phát triển bất thường của tế bào."
      }
    },
    {
      "id": "B_XICH_BACH_DAI",
      "label": "Benh",
      "properties": {
        "canonical_name": "Bệnh Xích Bạch đới",
        "aliases": [
          "xich bach doi",
          "xích bạch đới",
          "xichbachdoi"
        ],
        "search_vector_hint": "Bệnh Xích Bạch đới thuộc nhóm Bệnh, thường liên quan đến y học cổ truyền."
      }
    },
    {
      "id": "CN_TAN_U_HUYET",
      "label": "CongNang",
      "properties": {
        "canonical_name": "Công năng Tán ứ huyết",
        "aliases": [
          "khuu",
          "khứ ứ",
          "khu u",
          "tan u huyet",
          "phá huyết",
          "tanuhuyet",
          "phahuyet",
          "pha huyet",
          "tán ứ huyết"
        ],
        "search_vector_hint": "Tán ứ huyết thuộc nhóm Công năng."
      }
    },
    {
      "id": "CN_THANH_HUYET_NHIET",
      "label": "CongNang",
      "properties": {
        "canonical_name": "Công năng Thanh huyết nhiệt",
        "aliases": [
          "thanhhuyetnhiet",
          "thanh huyet nhiet",
          "thanh huyết nhiệt"
        ],
        "search_vector_hint": "Công năng Thanh huyết nhiệt thuộc nhóm công năng, thường liên quan đến làm mát máu, giải nhiệt."
      }
    },
    {
      "id": "DL_DIEU_KINH",
      "label": "DuocLy",
      "properties": {
        "canonical_name": "Tính chất Điều kinh",
        "aliases": [
          "chat dieu kinh",
          "chatdieukinh",
          "chất điều kinh"
        ],
        "search_vector_hint": "Điều kinh thuộc nhóm dược lý, thường liên quan đến kinh nguyệt."
      }
    },
    {
      "id": "DL_HA_SOT",
      "label": "DuocLy",
      "properties": {
        "canonical_name": "Điều trị Hạ sốt",
        "aliases": [
          "dieutrihasot",
          "dieu tri ha sot",
          "điều trị hạ sốt"
        ],
        "search_vector_hint": "Điều trị Hạ sốt thuộc nhóm điều trị, thường liên quan đến các bệnh lý gây sốt."
      }
    },
    {
      "id": "DL_KANG_KHUAN",
      "label": "DuocLy",
      "properties": {
        "canonical_name": "Dược lý Kháng khuẩn",
        "aliases": [
          "kháng khuẩn",
          "khangkhuan",
          "khang khuan"
        ],
        "search_vector_hint": "Kháng khuẩn thuộc nhóm dược lý, thường liên quan đến khả năng ức chế vi khuẩn."
      }
    },
    {
      "id": "HC_ANCALOIT",
      "label": "HoatChat",
      "properties": {
        "canonical_name": "Hoạt chất Ancaloit",
        "aliases": [
          "ancaloit"
        ],
        "search_vector_hint": "Hoạt chất Ancaloit thuộc nhóm hoạt chất, thường liên quan đến tác dụng dược lý."
      }
    },
    {
      "id": "HC_AXIT_BENZOIC",
      "label": "HoatChat",
      "properties": {
        "canonical_name": "Hoạt chất Axit Benzoic",
        "aliases": [
          "axitbenzoic",
          "axit benzoic"
        ],
        "search_vector_hint": "Hoạt chất Axit Benzoic thuộc nhóm hoạt chất."
      }
    },
    {
      "id": "HC_GLUCOZIT",
      "label": "HoatChat",
      "properties": {
        "canonical_name": "Hoạt chất Glucozit",
        "aliases": [
          "glucozit"
        ],
        "search_vector_hint": "Glucozit thuộc nhóm hoạt chất, thường liên quan đến các hợp chất hóa học."
      }
    },
    {
      "id": "HC_PAEONOLA",
      "label": "HoatChat",
      "properties": {
        "canonical_name": "Hoạt chất Paeonola",
        "aliases": [
          "paeonola"
        ],
        "search_vector_hint": "Hoạt chất Paeonola thuộc nhóm hoạt chất, thường liên quan đến thành phần hóa học."
      }
    },
    {
      "id": "HC_PHYTOSTEROL",
      "label": "HoatChat",
      "properties": {
        "canonical_name": "Hoạt chất Phytosterol",
        "aliases": [
          "phytosterol"
        ],
        "search_vector_hint": "Hoạt chất Phytosterol thuộc nhóm hoạt chất, thường liên quan đến tác dụng dược lý."
      }
    },
    {
      "id": "HC_SAPONIN",
      "label": "HoatChat",
      "properties": {
        "canonical_name": "Hoạt chất Saponin",
        "aliases": [
          "saponin"
        ],
        "search_vector_hint": "Hoạt chất Saponin thuộc nhóm hoạt chất, thường liên quan đến tác dụng dược lý."
      }
    },
    {
      "id": "K_CAN",
      "label": "KinhMach",
      "properties": {
        "canonical_name": "Can",
        "aliases": [
          "can"
        ],
        "search_vector_hint": "Kinh Can thuộc nhóm kinh."
      }
    },
    {
      "id": "K_TAM",
      "label": "KinhMach",
      "properties": {
        "canonical_name": "Tam",
        "aliases": [
          "tam bao",
          "tam bảo",
          "tambao"
        ],
        "search_vector_hint": "Tam Bảo thuộc nhóm Kinh, thường liên quan đến hệ kinh lạc trong cơ thể."
      }
    },
    {
      "id": "K_THAN",
      "label": "KinhMach",
      "properties": {
        "canonical_name": "Than",
        "aliases": [
          "thận",
          "than"
        ],
        "search_vector_hint": "Kinh Thận thuộc nhóm Kinh, thường liên quan đến hệ kinh lạc trong cơ thể."
      }
    },
    {
      "id": "S_DAU_BUNG_KINH",
      "label": "TrieuChung",
      "properties": {
        "canonical_name": "Triệu chứng Đau bụng kinh",
        "aliases": [
          "thongkinh",
          "đau bụng kinh",
          "thống kinh",
          "thong kinh",
          "daubungkinh",
          "dau bung kinh"
        ],
        "search_vector_hint": "Triệu chứng Đau bụng kinh thuộc nhóm Triệu chứng, thường liên quan đến kinh nguyệt."
      }
    },
    {
      "id": "S_DAU_DAU",
      "label": "TrieuChung",
      "properties": {
        "canonical_name": "Triệu chứng Đau đầu",
        "aliases": [
          "nhức đầu",
          "daudau",
          "dau dau",
          "đau đầu",
          "nhuc dau",
          "nhucdau"
        ],
        "search_vector_hint": "Triệu chứng Đau đầu thuộc nhóm Triệu chứng, thường liên quan đến căng thẳng, stress."
      }
    },
    {
      "id": "S_KHAT_NUOC",
      "label": "TrieuChung",
      "properties": {
        "canonical_name": "Triệu chứng Khát nước",
        "aliases": [
          "haonuoc",
          "khatnuoc",
          "háo nước",
          "khat nuoc",
          "hao nuoc",
          "khát nước"
        ],
        "search_vector_hint": "Triệu chứng Khát nước thuộc nhóm triệu chứng, thường liên quan đến mất nước hoặc bệnh lý nội tiết."
      }
    },
    {
      "id": "T_HAN",
      "label": "TinhVi",
      "properties": {
        "canonical_name": "Han",
        "aliases": [
          "han",
          "hàn"
        ],
        "search_vector_hint": "Hàn thuộc nhóm Tính."
      }
    },
    {
      "id": "VT_BACH_THUOC",
      "label": "ViThuoc",
      "properties": {
        "canonical_name": "Vị thuốc Bạch thược",
        "aliases": [
          "thuoc duoc",
          "kimthuocduoc",
          "kim thuoc duoc",
          "bachthuoc",
          "bach thuoc",
          "kim thược dược",
          "thược dược",
          "bạch thược",
          "thuocduoc"
        ],
        "search_vector_hint": "Vị thuốc Bạch thược thuộc nhóm vị thuốc, thường liên quan đến điều hòa kinh nguyệt, giảm đau."
      }
    },
    {
      "id": "VT_BACH_TRUAT",
      "label": "ViThuoc",
      "properties": {
        "canonical_name": "Vị thuốc Bạch truật",
        "aliases": [
          "bach truat",
          "bạch truật",
          "bachtruat"
        ],
        "search_vector_hint": "Vị thuốc Bạch truật thuộc nhóm Vị thuốc, thường liên quan đến kiện tỳ, táo thấp."
      }
    },
    {
      "id": "VT_CAM_THAO",
      "label": "ViThuoc",
      "properties": {
        "canonical_name": "Vị thuốc Cam thảo",
        "aliases": [
          "cam thảo",
          "camthao",
          "cam thao"
        ],
        "search_vector_hint": "Vị thuốc Cam thảo thuộc nhóm vị thuốc, thường liên quan đến bổ khí, giải độc."
      }
    },
    {
      "id": "VT_DAI_HOANG",
      "label": "ViThuoc",
      "properties": {
        "canonical_name": "Vị thuốc Đại hoàng",
        "aliases": [
          "dai hoang",
          "daihoang",
          "đại hoàng"
        ],
        "search_vector_hint": "Vị thuốc Đại hoàng thuộc nhóm vị thuốc, thường liên quan đến điều trị bệnh lý."
      }
    },
    {
      "id": "VT_DAO_NHAN",
      "label": "ViThuoc",
      "properties": {
        "canonical_name": "Vị thuốc Đào nhân",
        "aliases": [
          "dao nhan",
          "đào nhân",
          "daonhan"
        ],
        "search_vector_hint": "Vị thuốc Đào nhân thuộc nhóm Vị thuốc, thường liên quan đến hoạt huyết, phá huyết."
      }
    },
    {
      "id": "VT_DUONG_QUY",
      "label": "ViThuoc",
      "properties": {
        "canonical_name": "Vị thuốc Đương quy",
        "aliases": [
          "duongquy",
          "duong quy",
          "đương quy"
        ],
        "search_vector_hint": "Vị thuốc Đương quy thuộc nhóm Vị thuốc, thường liên quan đến bổ huyết, hoạt huyết."
      }
    },
    {
      "id": "VT_HOANG_BA",
      "label": "ViThuoc",
      "properties": {
        "canonical_name": "Vị thuốc Hoàng bá",
        "aliases": [
          "hoang ba",
          "hoangba",
          "hoàng bá"
        ],
        "search_vector_hint": "Vị thuốc Hoàng bá thuộc nhóm vị thuốc, thường liên quan đến thanh nhiệt giải độc."
      }
    },
    {
      "id": "VT_HOANG_CAM",
      "label": "ViThuoc",
      "properties": {
        "canonical_name": "Vị thuốc Hoàng cầm",
        "aliases": [
          "hoang cam",
          "hoàng cầm",
          "hoangcam"
        ],
        "search_vector_hint": "Vị thuốc Hoàng cầm thuộc nhóm vị thuốc, thường liên quan đến điều trị bệnh lý."
      }
    },
    {
      "id": "VT_HUONG_PHU",
      "label": "ViThuoc",
      "properties": {
        "canonical_name": "Vị thuốc Hương phụ",
        "aliases": [
          "huong phu",
          "huongphu",
          "hương phụ"
        ],
        "search_vector_hint": "Vị thuốc Hương phụ thuộc nhóm Vị thuốc, thường liên quan đến hành khí, giải uất, điều kinh."
      }
    },
    {
      "id": "VT_MANG_TIEU",
      "label": "ViThuoc",
      "properties": {
        "canonical_name": "Vị thuốc Mang tiêu",
        "aliases": [
          "mang tieu",
          "mang tiêu",
          "mangtieu"
        ],
        "search_vector_hint": "Mang tiêu thuộc nhóm Vị thuốc, thường liên quan đến các bài thuốc y học cổ truyền."
      }
    },
    {
      "id": "VT_MAU_DON_BI",
      "label": "ViThuoc",
      "properties": {
        "canonical_name": "Vị thuốc Mẫu đơn bì",
        "aliases": [
          "donbi",
          "mau don bi",
          "đơn bì",
          "mẫu đơn bì",
          "don bi",
          "maudonbi"
        ],
        "search_vector_hint": "Vị thuốc Mẫu đơn bì thuộc nhóm Vị thuốc, thường liên quan đến điều trị bệnh lý.",
        "lieu_dung_chung": "Ngày dùng $5-10g$ dưới dạng thuốc sắc; Ngày dùng $6-12g$ dưới dạng thuốc sắc.",
        "muc_do_doc": "Không độc",
        "bo_phan_dung": "vỏ rễ",
        "phan_bo": "Trung Quốc, Việt Nam (Sa Pa, Tam Đảo)",
        "thu_hai": "tháng 8-9",
        "che_bien_tho": "đào lấy rễ, rửa sạch đất cát, cạo bỏ vỏ ngoài, phơi khô",
        "ten_khoa_hoc": "$Paeonia suffruticosa Andr. (Paeonia arborea Donn, Paeonia moutan Sims.); Paeonia suffruticosa Andr. (Paeonia moutan Sims)$",
        "ho_thuc_vat": "$Mao lương Ranunculaceae; Hoàng liên Ranunculaceae$",
        "hinh_thai_chi_tiet": "Mẫu đơn là một cây nhỏ, cao 1-2m. Thân thẳng, ít phân cành. Lá mọc so le, kép lông chim 2 lần, không có lá kèm. Hoa rất to, mọc riêng lẻ ở đầu cành, màu trắng hay đỏ, đường kính có thể đạt tới 10-20cm. Quả có 3-5 đại, khi chín thì mở ra.",
        "lieu_dung_tong_quat": "Không có thông tin",
        "ghi_chu_bo_sung": "Không có thông tin",
        "cach_dung_bao_che": "Không có thông tin"
      }
    },
    {
      "id": "VT_PHUC_LINH",
      "label": "ViThuoc",
      "properties": {
        "canonical_name": "Vị thuốc Phục linh",
        "aliases": [
          "phuc linh",
          "phục linh",
          "phuclinh"
        ],
        "search_vector_hint": "Vị thuốc Phục linh thuộc nhóm vị thuốc, thường liên quan đến ..."
      }
    },
    {
      "id": "VT_QUE_CHI",
      "label": "ViThuoc",
      "properties": {
        "canonical_name": "Vị thuốc Quế chi",
        "aliases": [
          "quế chi",
          "que chi",
          "quechi"
        ],
        "search_vector_hint": "Vị thuốc Quế chi thuộc nhóm vị thuốc, thường liên quan đến các bài thuốc cổ truyền."
      }
    },
    {
      "id": "VT_SAI_HO",
      "label": "ViThuoc",
      "properties": {
        "canonical_name": "Vị thuốc Sài hồ",
        "aliases": [
          "sai ho",
          "sài hồ",
          "saiho"
        ],
        "search_vector_hint": "Vị thuốc Sài hồ thuộc nhóm Vị thuốc, thường liên quan đến sơ can, giải uất, thoái nhiệt."
      }
    },
    {
      "id": "VT_SINH_DIA",
      "label": "ViThuoc",
      "properties": {
        "canonical_name": "Vị thuốc Sinh địa",
        "aliases": [
          "sinh địa",
          "sinh dia",
          "sinhdia"
        ],
        "search_vector_hint": "Sinh địa thuộc nhóm vị thuốc, thường liên quan đến các bài thuốc cổ truyền."
      }
    },
    {
      "id": "VT_THUOC_DUOC",
      "label": "ViThuoc",
      "properties": {
        "canonical_name": "Vị thuốc Thuốc dột",
        "aliases": [
          "thuoc dot",
          "thuốc dột",
          "thuocdot"
        ],
        "search_vector_hint": "Vị thuốc Thuốc dột thuộc nhóm vị thuốc, thường liên quan đến ..."
      }
    },
    {
      "id": "VT_TRACH_TA",
      "label": "ViThuoc",
      "properties": {
        "canonical_name": "Vị thuốc Trạch tả",
        "aliases": [
          "trạch tả",
          "trachta",
          "trach ta"
        ],
        "search_vector_hint": "Vị thuốc Trạch tả thuộc nhóm Vị thuốc, thường liên quan đến lợi tiểu, thẩm thấp."
      }
    },
    {
      "id": "VT_TRAN_BI",
      "label": "ViThuoc",
      "properties": {
        "canonical_name": "Vị thuốc Trần bì",
        "aliases": [
          "trần bì",
          "vo quyt",
          "voquyt",
          "quýt",
          "vỏ quýt",
          "tran bi",
          "tranbi",
          "quyt"
        ],
        "search_vector_hint": "Vị thuốc Trần bì thuộc nhóm vị thuốc, thường liên quan đến kiện tỳ, lý khí, hóa đàm."
      }
    },
    {
      "id": "VT_TRI_MAU",
      "label": "ViThuoc",
      "properties": {
        "canonical_name": "Vị thuốc Tri mẫu",
        "aliases": [
          "trimau",
          "tri mẫu",
          "tri mau"
        ],
        "search_vector_hint": "Tri mẫu thuộc nhóm Vị thuốc, thường liên quan đến thanh nhiệt giáng hỏa."
      }
    },
    {
      "id": "V_CAY",
      "label": "TinhVi",
      "properties": {
        "canonical_name": "Cay",
        "aliases": [
          "cây",
          "cay"
        ],
        "search_vector_hint": "Vị thuốc Cây thuộc nhóm vị thuốc, thường liên quan đến điều trị bệnh lý."
      }
    },
    {
      "id": "V_DANG",
      "label": "TinhVi",
      "properties": {
        "canonical_name": "Dang",
        "aliases": [
          "đắng",
          "dang"
        ],
        "search_vector_hint": "Đắng thuộc nhóm tính vị."
      }
    }
  ],
  "claims": [
    {
      "source": {
        "source_id": "CT_VT_VN_T637",
        "ten_sach": "Những cây thuốc và vị thuốc Việt Nam",
        "tac_gia": "Đỗ Tất Lợi",
        "trang": "637"
      },
      "dac_tinh_yhct": {
        "vi": [
          "V_TAN",
          "V_DANG_KHO"
        ],
        "tinh": "T_HOI_HAN",
        "quy_kinh": [
          "K_TAM",
          "K_TAM_BAO",
          "K_THAN",
          "K_CAN"
        ],
        "cong_nang": "thanh huyết nhiệt, tán ứ huyết"
      },
      "mo_ta_theo_nguon": {
        "hinh_thai_chi_tiet": "Mẫu đơn là một cây nhỏ, cao 1-2m. Thân thẳng, ít phân cành. Lá mọc so le, kép lông chim 2 lần, không có lá kèm. Hoa rất to, mọc riêng lẻ ở đầu cành, màu trắng hay đỏ, đường kính có thể đạt tới 10-20cm. Quả có 3-5 đại, khi chín thì mở ra.",
        "thanh_phan_hoa_hoc": [],
        "lieu_dung_tong_quat": "Không có thông tin",
        "ghi_chu_bo_sung": "Không có thông tin",
        "cach_dung_bao_che": "Không có thông tin"
      },
      "confidence_score": 0.95
    }
  ],
  "relationships": [
    {
      "from": "VT_MAU_DON_BI",
      "to": "V_CAY",
      "relation_type": "CO_VI",
      "properties": {
        "mo_ta_chi_tiet": "vị cay"
      },
      "source": {
        "source_id": "CT_VT_VN_T637",
        "all_sources": [
          "CT_VT_VN_T637"
        ]
      },
      "confidence_score": 0.75
    },
    {
      "from": "VT_MAU_DON_BI",
      "to": "V_DANG",
      "relation_type": "CO_VI",
      "properties": {
        "mo_ta_chi_tiet": "vị đắng"
      },
      "source": {
        "source_id": "CT_VT_VN_T637",
        "all_sources": [
          "CT_VT_VN_T637"
        ]
      },
      "confidence_score": 0.75
    },
    {
      "from": "VT_MAU_DON_BI",
      "to": "T_HAN",
      "relation_type": "CO_TINH",
      "properties": {
        "mo_ta_chi_tiet": "tính hơi hàn"
      },
      "source": {
        "source_id": "CT_VT_VN_T637",
        "all_sources": [
          "CT_VT_VN_T637"
        ]
      },
      "confidence_score": 0.75
    },
    {
      "from": "VT_MAU_DON_BI",
      "to": "K_TAM",
      "relation_type": "QUY_KINH",
      "properties": {
        "mo_ta_chi_tiet": "vào kinh tâm | vào kinh tâm bào"
      },
      "source": {
        "source_id": "CT_VT_VN_T637",
        "all_sources": [
          "CT_VT_VN_T637"
        ]
      },
      "confidence_score": 0.75
    },
    {
      "from": "VT_MAU_DON_BI",
      "to": "K_CAN",
      "relation_type": "QUY_KINH",
      "properties": {
        "mo_ta_chi_tiet": "vào kinh can"
      },
      "source": {
        "source_id": "CT_VT_VN_T637",
        "all_sources": [
          "CT_VT_VN_T637"
        ]
      },
      "confidence_score": 0.75
    },
    {
      "from": "VT_MAU_DON_BI",
      "to": "K_THAN",
      "relation_type": "QUY_KINH",
      "properties": {
        "mo_ta_chi_tiet": "vào kinh thận"
      },
      "source": {
        "source_id": "CT_VT_VN_T637",
        "all_sources": [
          "CT_VT_VN_T637"
        ]
      },
      "confidence_score": 0.75
    },
    {
      "from": "VT_MAU_DON_BI",
      "to": "HC_PAEONOLA",
      "relation_type": "CO_CHUA_HOAT_CHAT",
      "properties": {
        "mo_ta_chi_tiet": "Trong mẫu đơn bì tươi có một glucozit, khi chất glucozit này tiếp xúc với một chất men có trong vỏ cây này, sẽ cho glucoza và $paeonola$ là một chất phenola.",
        "ghi_chu": "Không có thông tin"
      },
      "confidence_score": 0.75,
      "source": {
        "source_id": "CT_VT_VN_T637",
        "all_sources": [
          "CT_VT_VN_T637"
        ]
      }
    },
    {
      "from": "VT_MAU_DON_BI",
      "to": "HC_AXIT_BENZOIC",
      "relation_type": "CO_CHUA_HOAT_CHAT",
      "properties": {
        "mo_ta_chi_tiet": "Ngoài ra còn axit benzoic, phytosterol.",
        "ghi_chu": "Không có thông tin"
      },
      "confidence_score": 0.75,
      "source": {
        "source_id": "CT_VT_VN_T637",
        "all_sources": [
          "CT_VT_VN_T637"
        ]
      }
    },
    {
      "from": "VT_MAU_DON_BI",
      "to": "HC_PHYTOSTEROL",
      "relation_type": "CO_CHUA_HOAT_CHAT",
      "properties": {
        "mo_ta_chi_tiet": "Ngoài ra còn axit benzoic, phytosterol.",
        "ghi_chu": "Không có thông tin"
      },
      "confidence_score": 0.75,
      "source": {
        "source_id": "CT_VT_VN_T637",
        "all_sources": [
          "CT_VT_VN_T637"
        ]
      }
    },
    {
      "from": "VT_MAU_DON_BI",
      "to": "HC_GLUCOZIT",
      "relation_type": "CO_CHUA_HOAT_CHAT",
      "properties": {
        "mo_ta_chi_tiet": "Năm 1958, Viện y học Bắc Kinh phân tích thấy trong mẫu đơn bì Tứ Xuyên có $5,66\\%$ glucozit, $0,4\\%$ ancaloit, $12,54\\%$ saponin.",
        "ghi_chu": "Không có thông tin"
      },
      "confidence_score": 0.75,
      "source": {
        "source_id": "CT_VT_VN_T637",
        "all_sources": [
          "CT_VT_VN_T637"
        ]
      }
    },
    {
      "from": "VT_MAU_DON_BI",
      "to": "HC_ANCALOIT",
      "relation_type": "CO_CHUA_HOAT_CHAT",
      "properties": {
        "mo_ta_chi_tiet": "Năm 1958, Viện y học Bắc Kinh phân tích thấy trong mẫu đơn bì Tứ Xuyên có $5,66\\%$ glucozit, $0,4\\%$ ancaloit, $12,54\\%$ saponin.",
        "ghi_chu": "Không có thông tin"
      },
      "confidence_score": 0.75,
      "source": {
        "source_id": "CT_VT_VN_T637",
        "all_sources": [
          "CT_VT_VN_T637"
        ]
      }
    },
    {
      "from": "VT_MAU_DON_BI",
      "to": "HC_SAPONIN",
      "relation_type": "CO_CHUA_HOAT_CHAT",
      "properties": {
        "mo_ta_chi_tiet": "Năm 1958, Viện y học Bắc Kinh phân tích thấy trong mẫu đơn bì Tứ Xuyên có $5,66\\%$ glucozit, $0,4\\%$ ancaloit, $12,54\\%$ saponin.",
        "ghi_chu": "Không có thông tin"
      },
      "confidence_score": 0.75,
      "source": {
        "source_id": "CT_VT_VN_T637",
        "all_sources": [
          "CT_VT_VN_T637"
        ]
      }
    },
    {
      "from": "BT_TRUOC_DE_DON_BI",
      "to": "VT_MAU_DON_BI",
      "relation_type": "BAO_GOM_VI_THUOC",
      "properties": {
        "loai_che_pham": "Cổ phương",
        "lieu_luong": "$5g$ | $8g$",
        "vai_tro": "Quân"
      },
      "source": {
        "source_id": "CT_VT_VN_T637",
        "all_sources": [
          "CT_VT_VN_T637"
        ]
      },
      "confidence_score": 0.75
    },
    {
      "from": "BT_TRUOC_DE_DON_BI",
      "to": "VT_DUONG_QUY",
      "relation_type": "BAO_GOM_VI_THUOC",
      "properties": {
        "loai_che_pham": "Cổ phương",
        "lieu_luong": "$5g$ | $12g$",
        "vai_tro": "Chưa rõ"
      },
      "source": {
        "source_id": "CT_VT_VN_T637",
        "all_sources": [
          "CT_VT_VN_T637"
        ]
      },
      "confidence_score": 0.75
    },
    {
      "from": "BT_TRUOC_DE_DON_BI",
      "to": "VT_THUOC_DUOC",
      "relation_type": "BAO_GOM_VI_THUOC",
      "properties": {
        "loai_che_pham": "Cổ phương",
        "lieu_luong": "$3g$",
        "vai_tro": "Tá"
      },
      "source": {
        "source_id": "CT_VT_VN_T637",
        "all_sources": [
          "CT_VT_VN_T637"
        ]
      },
      "confidence_score": 0.75
    },
    {
      "from": "BT_TRUOC_DE_DON_BI",
      "to": "VT_SINH_DIA",
      "relation_type": "BAO_GOM_VI_THUOC",
      "properties": {
        "loai_che_pham": "Cổ phương",
        "lieu_luong": "$6g$",
        "vai_tro": "Tá"
      },
      "source": {
        "source_id": "CT_VT_VN_T637",
        "all_sources": [
          "CT_VT_VN_T637"
        ]
      },
      "confidence_score": 0.75
    },
    {
      "from": "BT_TRUOC_DE_DON_BI",
      "to": "VT_TRAN_BI",
      "relation_type": "BAO_GOM_VI_THUOC",
      "properties": {
        "loai_che_pham": "Cổ phương",
        "lieu_luong": "$4g$",
        "vai_tro": "Tá"
      },
      "source": {
        "source_id": "CT_VT_VN_T637",
        "all_sources": [
          "CT_VT_VN_T637"
        ]
      },
      "confidence_score": 0.75
    },
    {
      "from": "BT_TRUOC_DE_DON_BI",
      "to": "VT_BACH_TRUAT",
      "relation_type": "BAO_GOM_VI_THUOC",
      "properties": {
        "loai_che_pham": "Cổ phương",
        "lieu_luong": "$4g$",
        "vai_tro": "Tá"
      },
      "source": {
        "source_id": "CT_VT_VN_T637",
        "all_sources": [
          "CT_VT_VN_T637"
        ]
      },
      "confidence_score": 0.75
    },
    {
      "from": "BT_TRUOC_DE_DON_BI",
      "to": "VT_HUONG_PHU",
      "relation_type": "BAO_GOM_VI_THUOC",
      "properties": {
        "loai_che_pham": "Cổ phương",
        "lieu_luong": "$3g$",
        "vai_tro": "Tá"
      },
      "source": {
        "source_id": "CT_VT_VN_T637",
        "all_sources": [
          "CT_VT_VN_T637"
        ]
      },
      "confidence_score": 0.75
    },
    {
      "from": "BT_TRUOC_DE_DON_BI",
      "to": "VT_SAI_HO",
      "relation_type": "BAO_GOM_VI_THUOC",
      "properties": {
        "loai_che_pham": "Cổ phương",
        "lieu_luong": "$2g$",
        "vai_tro": "Tá"
      },
      "source": {
        "source_id": "CT_VT_VN_T637",
        "all_sources": [
          "CT_VT_VN_T637"
        ]
      },
      "confidence_score": 0.75
    },
    {
      "from": "BT_TRUOC_DE_DON_BI",
      "to": "VT_HOANG_CAM",
      "relation_type": "BAO_GOM_VI_THUOC",
      "properties": {
        "loai_che_pham": "Cổ phương",
        "lieu_luong": "$2g$",
        "vai_tro": "Tá"
      },
      "source": {
        "source_id": "CT_VT_VN_T637",
        "all_sources": [
          "CT_VT_VN_T637"
        ]
      },
      "confidence_score": 0.75
    },
    {
      "from": "BT_TRUOC_DE_DON_BI",
      "to": "VT_CAM_THAO",
      "relation_type": "BAO_GOM_VI_THUOC",
      "properties": {
        "loai_che_pham": "Cổ phương",
        "lieu_luong": "$2g$",
        "vai_tro": "Sứ"
      },
      "source": {
        "source_id": "CT_VT_VN_T637",
        "all_sources": [
          "CT_VT_VN_T637"
        ]
      },
      "confidence_score": 0.75
    },
    {
      "from": "BT_TRUOC_DE_DON_BI",
      "to": "B_KINH_NGUYET_KHONG_DEU",
      "relation_type": "CHU_TRI_BENH",
      "properties": {
        "doi_tuong_thu_huong": "Người"
      },
      "source": {
        "source_id": "CT_VT_VN_T637",
        "all_sources": [
          "CT_VT_VN_T637"
        ]
      },
      "confidence_score": 0.75
    },
    {
      "from": "BT_TRUOC_DE_DON_BI",
      "to": "B_SAU_DE",
      "relation_type": "CHU_TRI_BENH",
      "properties": {
        "doi_tuong_thu_huong": "Người"
      },
      "source": {
        "source_id": "CT_VT_VN_T637",
        "all_sources": [
          "CT_VT_VN_T637"
        ]
      },
      "confidence_score": 0.75
    },
    {
      "from": "BT_TRUOC_DE_DON_BI",
      "to": "VT_BACH_THUOC",
      "relation_type": "BAO_GOM_VI_THUOC",
      "properties": {
        "loai_che_pham": "Cổ phương",
        "lieu_luong": "$12g$",
        "vai_tro": "Thần"
      },
      "source": {
        "source_id": "CT_VT_VN_T637",
        "all_sources": [
          "CT_VT_VN_T637"
        ]
      },
      "confidence_score": 0.75
    },
    {
      "from": "BT_TRUOC_DE_DON_BI",
      "to": "VT_PHUC_LINH",
      "relation_type": "BAO_GOM_VI_THUOC",
      "properties": {
        "loai_che_pham": "Cổ phương",
        "lieu_luong": "$8g$",
        "vai_tro": "Tá"
      },
      "source": {
        "source_id": "CT_VT_VN_T637",
        "all_sources": [
          "CT_VT_VN_T637"
        ]
      },
      "confidence_score": 0.75
    },
    {
      "from": "BT_TRUOC_DE_DON_BI",
      "to": "VT_TRACH_TA",
      "relation_type": "BAO_GOM_VI_THUOC",
      "properties": {
        "loai_che_pham": "Cổ phương",
        "lieu_luong": "$8g$",
        "vai_tro": "Tá"
      },
      "source": {
        "source_id": "CT_VT_VN_T637",
        "all_sources": [
          "CT_VT_VN_T637"
        ]
      },
      "confidence_score": 0.75
    },
    {
      "from": "BT_TRUOC_DE_DON_BI",
      "to": "B_XICH_BACH_DAI",
      "relation_type": "CHU_TRI_BENH",
      "properties": {
        "doi_tuong_thu_huong": "Người"
      },
      "source": {
        "source_id": "CT_VT_VN_T637",
        "all_sources": [
          "CT_VT_VN_T637"
        ]
      },
      "confidence_score": 0.75
    },
    {
      "from": "BT_TRUOC_DE_DON_BI",
      "to": "B_TRUOC_DE",
      "relation_type": "CHU_TRI_BENH",
      "properties": {
        "doi_tuong_thu_huong": "Người"
      },
      "source": {
        "source_id": "CT_VT_VN_T637",
        "all_sources": [
          "CT_VT_VN_T637"
        ]
      },
      "confidence_score": 0.75
    },
    {
      "from": "BT_KHAT_NUOC_DON_BI",
      "to": "VT_MAU_DON_BI",
      "relation_type": "BAO_GOM_VI_THUOC",
      "properties": {
        "loai_che_pham": "Cổ phương",
        "lieu_luong": "$12g$",
        "vai_tro": "Quân"
      },
      "source": {
        "source_id": "CT_VT_VN_T637",
        "all_sources": [
          "CT_VT_VN_T637"
        ]
      },
      "confidence_score": 0.75
    },
    {
      "from": "BT_KHAT_NUOC_DON_BI",
      "to": "VT_TRI_MAU",
      "relation_type": "BAO_GOM_VI_THUOC",
      "properties": {
        "loai_che_pham": "Cổ phương",
        "lieu_luong": "$8g$",
        "vai_tro": "Thần"
      },
      "source": {
        "source_id": "CT_VT_VN_T637",
        "all_sources": [
          "CT_VT_VN_T637"
        ]
      },
      "confidence_score": 0.75
    },
    {
      "from": "BT_KHAT_NUOC_DON_BI",
      "to": "VT_HOANG_BA",
      "relation_type": "BAO_GOM_VI_THUOC",
      "properties": {
        "loai_che_pham": "Cổ phương",
        "lieu_luong": "$8g$",
        "vai_tro": "Tá"
      },
      "source": {
        "source_id": "CT_VT_VN_T637",
        "all_sources": [
          "CT_VT_VN_T637"
        ]
      },
      "confidence_score": 0.75
    },
    {
      "from": "BT_KHAT_NUOC_DON_BI",
      "to": "VT_SINH_DIA",
      "relation_type": "BAO_GOM_VI_THUOC",
      "properties": {
        "loai_che_pham": "Cổ phương",
        "lieu_luong": "$20g$",
        "vai_tro": "Sứ"
      },
      "source": {
        "source_id": "CT_VT_VN_T637",
        "all_sources": [
          "CT_VT_VN_T637"
        ]
      },
      "confidence_score": 0.75
    },
    {
      "from": "BT_KHAT_NUOC_DON_BI",
      "to": "B_SOT_NONG",
      "relation_type": "CHU_TRI_BENH",
      "properties": {
        "doi_tuong_thu_huong": "Người"
      },
      "source": {
        "source_id": "CT_VT_VN_T637",
        "all_sources": [
          "CT_VT_VN_T637"
        ]
      },
      "confidence_score": 0.75
    },
    {
      "from": "BT_KHAT_NUOC_DON_BI",
      "to": "S_DAU_DAU",
      "relation_type": "CHU_TRI_TRIEU_CHUNG",
      "properties": {
        "doi_tuong_thu_huong": "Người"
      },
      "source": {
        "source_id": "CT_VT_VN_T637",
        "all_sources": [
          "CT_VT_VN_T637"
        ]
      },
      "confidence_score": 0.75
    },
    {
      "from": "BT_KHAT_NUOC_DON_BI",
      "to": "S_KHAT_NUOC",
      "relation_type": "CHU_TRI_TRIEU_CHUNG",
      "properties": {
        "doi_tuong_thu_huong": "Người"
      },
      "source": {
        "source_id": "CT_VT_VN_T637",
        "all_sources": [
          "CT_VT_VN_T637"
        ]
      },
      "confidence_score": 0.75
    },
    {
      "from": "BT_U_CUC_DON_BI",
      "to": "VT_MAU_DON_BI",
      "relation_type": "BAO_GOM_VI_THUOC",
      "properties": {
        "loai_che_pham": "Cổ phương",
        "lieu_luong": "$12g$",
        "vai_tro": "Quân"
      },
      "source": {
        "source_id": "CT_VT_VN_T637",
        "all_sources": [
          "CT_VT_VN_T637"
        ]
      },
      "confidence_score": 0.75
    },
    {
      "from": "BT_U_CUC_DON_BI",
      "to": "VT_DAO_NHAN",
      "relation_type": "BAO_GOM_VI_THUOC",
      "properties": {
        "loai_che_pham": "Cổ phương",
        "lieu_luong": "$12g$",
        "vai_tro": "Thần"
      },
      "source": {
        "source_id": "CT_VT_VN_T637",
        "all_sources": [
          "CT_VT_VN_T637"
        ]
      },
      "confidence_score": 0.75
    },
    {
      "from": "BT_U_CUC_DON_BI",
      "to": "VT_QUE_CHI",
      "relation_type": "BAO_GOM_VI_THUOC",
      "properties": {
        "loai_che_pham": "Cổ phương",
        "lieu_luong": "$4g$",
        "vai_tro": "Tá"
      },
      "source": {
        "source_id": "CT_VT_VN_T637",
        "all_sources": [
          "CT_VT_VN_T637"
        ]
      },
      "confidence_score": 0.75
    },
    {
      "from": "BT_U_CUC_DON_BI",
      "to": "VT_DAI_HOANG",
      "relation_type": "BAO_GOM_VI_THUOC",
      "properties": {
        "loai_che_pham": "Cổ phương",
        "lieu_luong": "$8g$",
        "vai_tro": "Tá"
      },
      "source": {
        "source_id": "CT_VT_VN_T637",
        "all_sources": [
          "CT_VT_VN_T637"
        ]
      },
      "confidence_score": 0.75
    },
    {
      "from": "BT_U_CUC_DON_BI",
      "to": "VT_MANG_TIEU",
      "relation_type": "BAO_GOM_VI_THUOC",
      "properties": {
        "loai_che_pham": "Cổ phương",
        "lieu_luong": "$4g$",
        "vai_tro": "Sứ"
      },
      "source": {
        "source_id": "CT_VT_VN_T637",
        "all_sources": [
          "CT_VT_VN_T637"
        ]
      },
      "confidence_score": 0.75
    },
    {
      "from": "BT_U_CUC_DON_BI",
      "to": "B_BE_KINH",
      "relation_type": "CHU_TRI_BENH",
      "properties": {
        "doi_tuong_thu_huong": "Người"
      },
      "source": {
        "source_id": "CT_VT_VN_T637",
        "all_sources": [
          "CT_VT_VN_T637"
        ]
      },
      "confidence_score": 0.75
    },
    {
      "from": "BT_U_CUC_DON_BI",
      "to": "S_DAU_BUNG_KINH",
      "relation_type": "CHU_TRI_TRIEU_CHUNG",
      "properties": {
        "doi_tuong_thu_huong": "Người"
      },
      "source": {
        "source_id": "CT_VT_VN_T637",
        "all_sources": [
          "CT_VT_VN_T637"
        ]
      },
      "confidence_score": 0.75
    },
    {
      "from": "BT_U_CUC_DON_BI",
      "to": "B_U_CUC",
      "relation_type": "CHU_TRI_BENH",
      "properties": {
        "doi_tuong_thu_huong": "Người"
      },
      "source": {
        "source_id": "CT_VT_VN_T637",
        "all_sources": [
          "CT_VT_VN_T637"
        ]
      },
      "confidence_score": 0.75
    },
    {
      "from": "VT_MAU_DON_BI",
      "to": "CN_THANH_HUYET_NHIET",
      "relation_type": "CO_CONG_NANG",
      "properties": {
        "mo_ta_chi_tiet": "Thanh huyết nhiệt."
      },
      "source": {
        "source_id": "CT_VT_VN_T637",
        "all_sources": [
          "CT_VT_VN_T637"
        ]
      },
      "confidence_score": 0.75
    },
    {
      "from": "VT_MAU_DON_BI",
      "to": "CN_TAN_U_HUYET",
      "relation_type": "CO_CONG_NANG",
      "properties": {
        "mo_ta_chi_tiet": "Tán ứ huyết."
      },
      "source": {
        "source_id": "CT_VT_VN_T637",
        "all_sources": [
          "CT_VT_VN_T637"
        ]
      },
      "confidence_score": 0.75
    },
    {
      "from": "VT_MAU_DON_BI",
      "to": "DL_HA_SOT",
      "relation_type": "CO_TAC_DUNG_DUOC_LY",
      "properties": {
        "mo_ta_chi_tiet": "Thí nghiệm trên thỏ, thấy mẫu đơn bì có tác dụng chữa sốt.",
        "ghi_chu": "Tác dụng hạ sốt trên thỏ có thể do thành phần axit benzoic."
      },
      "source": {
        "source_id": "CT_VT_VN_T637",
        "all_sources": [
          "CT_VT_VN_T637"
        ]
      },
      "confidence_score": 0.75
    },
    {
      "from": "VT_MAU_DON_BI",
      "to": "DL_KANG_KHUAN",
      "relation_type": "CO_TAC_DUNG_DUOC_LY",
      "properties": {
        "mo_ta_chi_tiet": "Mẫu đơn bì có tác dụng trên vi trùng thương hàn, thổ tả và lỵ."
      },
      "source": {
        "source_id": "CT_VT_VN_T637",
        "all_sources": [
          "CT_VT_VN_T637"
        ]
      },
      "confidence_score": 0.75
    },
    {
      "from": "VT_MAU_DON_BI",
      "to": "DL_DIEU_KINH",
      "relation_type": "CO_TAC_DUNG_DUOC_LY",
      "properties": {
        "mo_ta_chi_tiet": "$Paeonola$ có tác dụng gây sung huyết ở vùng tử cung động vật, do đó có tác dụng điều kinh, nhưng tác dụng yếu và chậm."
      },
      "source": {
        "source_id": "CT_VT_VN_T637",
        "all_sources": [
          "CT_VT_VN_T637"
        ]
      },
      "confidence_score": 0.75
    }
  ],
  "metadata": {
    "scientific_metrics": {
      "data_richness_index": 84.0,
      "reliability_c_score": 0.7539,
      "total_confidence_sum": 38.45
    },
    "validator_pass_score": 100,
    "processed_at": "2026-04-19 08:41:54"
  }
}