{
  "entity": {
    "entity_type": "VI_THUOC",
    "id": "VI_THUOC_KIM_NGAN",
    "ten_raw": "Kim ngân",
    "ten_khoa_hoc": "$Lonicera japonica Thunb.; Lonicera dasystyla Rehder; Lonicera confusa DC.$",
    "ho_thuc_vat": "$Họ Kim ngân (Caprifoliaceae)$",
    "variants": [
      "nhẫn đông"
    ],
    "properties": {
      "bo_phan_dung": "hoa, cành lá",
      "thu_hai": "tháng 4-5",
      "che_bien_tho": "không có thông tin",
      "lieu_dung_chung": "Ngày dùng $4$ đến $6g$ hoa hay $10$ đến $12g$ cành lá dưới dạng thuốc sắc, hay thuốc cao hoặc rượu thuốc.",
      "muc_do_doc": "Không độc",
      "trieu_chung_ngo_doc": "Một số người uống kim ngân đi ỉa lỏng, chỉ cần giảm liều xuống hoặc nghỉ uống là hết.",
      "phan_bo": "Kim ngân là một cây loại mọc hoang tại nhiều tỉnh vùng núi nước ta, nhiều nhất ở Cao Bằng, Lạng sơn, Ninh Bình, Thanh Hóa, Nghệ An, Hà Tĩnh, Bắc Giang, Thái Nguyên, Quảng Ninh, Vĩnh Phúc, Phú Thọ."
    },
    "display_name": "Kim ngân",
    "canonical_name": "Kim ngân"
  },
  "nodes": [
    {
      "id": "VI_THUOC_KIM_NGAN",
      "label": "ThucThe",
      "properties": {
        "canonical_name": "Thuoc Kim Ngan"
      }
    },
    {
      "id": "V_NGOT",
      "label": "Vi",
      "properties": {
        "canonical_name": "Ngot"
      }
    },
    {
      "id": "T_HAN",
      "label": "Tinh",
      "properties": {
        "canonical_name": "Han"
      }
    },
    {
      "id": "K_PHE",
      "label": "Kinh",
      "properties": {
        "canonical_name": "Phe"
      }
    },
    {
      "id": "K_VI",
      "label": "Kinh",
      "properties": {
        "canonical_name": "Vi"
      }
    },
    {
      "id": "K_TAM",
      "label": "Kinh",
      "properties": {
        "canonical_name": "Tam"
      }
    },
    {
      "id": "K_TY",
      "label": "Kinh",
      "properties": {
        "canonical_name": "Ty"
      }
    },
    {
      "id": "HC_INOZIT",
      "label": "HoatChat",
      "properties": {
        "canonical_name": "Inozit"
      }
    },
    {
      "id": "HC_LONIXERIN",
      "label": "HoatChat",
      "properties": {
        "canonical_name": "Lonixerin"
      }
    },
    {
      "id": "HC_SAPONOZIT",
      "label": "HoatChat",
      "properties": {
        "canonical_name": "Saponozit"
      }
    },
    {
      "id": "B_MUN_NHOT",
      "label": "Benh",
      "properties": {
        "canonical_name": "Mun Nhot"
      }
    },
    {
      "id": "B_ROM_SAY",
      "label": "Benh",
      "properties": {
        "canonical_name": "Rom Say"
      }
    },
    {
      "id": "B_LEN_DAU",
      "label": "Benh",
      "properties": {
        "canonical_name": "Len Dau"
      }
    },
    {
      "id": "B_LEN_SOI",
      "label": "Benh",
      "properties": {
        "canonical_name": "Len Soi"
      }
    },
    {
      "id": "B_SOT",
      "label": "Benh",
      "properties": {
        "canonical_name": "Sot"
      }
    },
    {
      "id": "B_MAN_NGUA",
      "label": "Benh",
      "properties": {
        "canonical_name": "Man Ngua"
      }
    },
    {
      "id": "B_SOT_NONG",
      "label": "Benh",
      "properties": {
        "canonical_name": "Sot Nong"
      }
    },
    {
      "id": "B_SOT_RET",
      "label": "Benh",
      "properties": {
        "canonical_name": "Sot Ret"
      }
    },
    {
      "id": "B_VIEM_MUI_DI_UNG",
      "label": "Benh",
      "properties": {
        "canonical_name": "Viem Mui Di Ung"
      }
    },
    {
      "id": "B_THAP_KHOP",
      "label": "Benh",
      "properties": {
        "canonical_name": "Thap Khop"
      }
    },
    {
      "id": "B_DI_UNG",
      "label": "Benh",
      "properties": {
        "canonical_name": "Di Ung"
      }
    },
    {
      "id": "BT_THONG_TIEU_KIM_NGAN",
      "label": "BaiThuoc",
      "properties": {
        "canonical_name": "Thong Tieu Kim Ngan"
      }
    },
    {
      "id": "VI_THUOC_KE_DAU_NGUA",
      "label": "ViThuoc",
      "properties": {
        "canonical_name": "Ke Dau Ngua"
      }
    },
    {
      "id": "VI_THUOC_CAM_THAO",
      "label": "ViThuoc",
      "properties": {
        "canonical_name": "Cam Thao"
      }
    },
    {
      "id": "BT_CAM_KIEU_TAN",
      "label": "BaiThuoc",
      "properties": {
        "canonical_name": "Cam Kieu Tan"
      }
    },
    {
      "id": "VI_THUOC_LIEN_KIEU",
      "label": "ViThuoc",
      "properties": {
        "canonical_name": "Lien Kieu"
      }
    },
    {
      "id": "VI_THUOC_KINH_GIOI_TUE",
      "label": "ViThuoc",
      "properties": {
        "canonical_name": "Kinh Gioi Tue"
      }
    },
    {
      "id": "VI_THUOC_CAT_CANH",
      "label": "ViThuoc",
      "properties": {
        "canonical_name": "Cat Canh"
      }
    },
    {
      "id": "VI_THUOC_DAM_DAU_SI",
      "label": "ViThuoc",
      "properties": {
        "canonical_name": "Dam Dau Si"
      }
    },
    {
      "id": "VI_THUOC_BAC_HA",
      "label": "ViThuoc",
      "properties": {
        "canonical_name": "Bac Ha"
      }
    },
    {
      "id": "VI_THUOC_NGUU_BANG_TU",
      "label": "ViThuoc",
      "properties": {
        "canonical_name": "Nguu Bang Tu"
      }
    },
    {
      "id": "VI_THUOC_DAM_TRUC_DIEP",
      "label": "ViThuoc",
      "properties": {
        "canonical_name": "Dam Truc Diep"
      }
    },
    {
      "id": "B_NGOT",
      "label": "Benh",
      "properties": {
        "canonical_name": "Cam"
      }
    },
    {
      "id": "CN_THANH_NHIET_GIAI_DOC",
      "label": "CongNang",
      "properties": {
        "canonical_name": "Thanh Nhiet Giai Doc"
      }
    },
    {
      "id": "CN_DIEN_NIEN",
      "label": "CongNang",
      "properties": {
        "canonical_name": "Dien Nien"
      }
    },
    {
      "id": "DL_KHANG_SINH",
      "label": "DuocLy",
      "properties": {
        "canonical_name": "Khang Sinh"
      }
    },
    {
      "id": "DL_KHANG_KHUAN",
      "label": "DuocLy",
      "properties": {
        "canonical_name": "Khang Khuan"
      }
    },
    {
      "id": "DL_DUONG_HUYET",
      "label": "DuocLy",
      "properties": {
        "canonical_name": "Duong Huyet"
      }
    },
    {
      "id": "DL_CHONG_CHOANG_PHAN_VE",
      "label": "DuocLy",
      "properties": {
        "canonical_name": "Chong Choang Phan Ve"
      }
    },
    {
      "id": "DL_DOC_TINH",
      "label": "DuocLy",
      "properties": {
        "canonical_name": "Doc Tinh"
      }
    },
    {
      "id": "CN_GIANG_MAI",
      "label": "CongNang",
      "properties": {
        "canonical_name": "Giang Mai"
      }
    },
    {
      "id": "CN_THONG_TIEU",
      "label": "CongNang",
      "properties": {
        "canonical_name": "Thong Tieu"
      }
    },
    {
      "id": "CN_TA_LY",
      "label": "CongNang",
      "properties": {
        "canonical_name": "Ta Ly"
      }
    }
  ],
  "claims": [
    {
      "source": {
        "source_id": "CT_VT_VN_T90",
        "ten_sach": "Những cây thuốc và vị thuốc Việt Nam",
        "tac_gia": "Đỗ Tất Lợi",
        "trang": "90"
      },
      "dac_tinh_yhct": {
        "vi": [
          "Ngọt (Cam)"
        ],
        "tinh": "Hàn",
        "quy_kinh": [
          "K_PHE",
          "K_VI",
          "K_TAM",
          "K_TY"
        ]
      },
      "mo_ta_theo_nguon": {
        "hinh_thai_chi_tiet": "Kim ngân là một loại dây mọc leo, thân có thể vươn dài tới $10m$ hay hơn. Cành lúc còn non màu lục nhạt, có phủ lông mịn, khi cành già chuyển màu nâu đỏ nhạt, nhẵn. Lá mọc đối, đôi khi mọc vòng 3 lá một, hình trứng dài, đầu hơi tù, phía cuống tròn, cuống ngắn $2-3mm$, cả hai mặt đều phủ lông mịn. Vào các tháng 5-8, hoa mọc từng đôi ở kẽ lá, mỗi kẽ lá có 1 cuống mang 2 hoa, hai bên lá mọc đối mang 4 hoa, lá bắc giống lá nhưng nhỏ hơn. Hoa hình ống xẻ hai môi, môi lớn lại xẻ thành 3 hay 4 thùy nhỏ, phiến của tràng dài gần bằng ống tràng, lúc đầu màu trắng, sau khi nở một thời gian chuyển màu vàng, cùng một lúc trên cây có hoa mới nở màu trắng như bạc, lại có hoa nở đã lâu màu vàng như vàng cho nên có tên là kim ngân (kim là vàng, ngân là bạc); cây kim ngân xanh tốt vào mùa đông cho nên còn có tên là nhẫn đông nghĩa là chịu đựng mùa đông, 4 nhị thòi dài cao hơn tràng; vòi nhụy lại thòi dài cao hơn nhị, mùi thơm dễ chịu. Quả hình trứng dài chừng $5 mm$ (Hình 37, Hm 4,3).",
        "thanh_phan_hoa_hoc": [
          "Theo Tăng Quảng Phương, trong hoa kim ngân có $inozit$ (hay $inozitol$) chừng $1\\%$.",
          "Theo Thang Đằng Hán, hoạt chất của kim ngân là một chất có trạng thái dầu, không bay hơi, có thể tan trong nước và trong các dung môi hữu cơ.",
          "Năm 1961, một số nhà nghiên cứu Nhật Bản cho biết trong kim ngân có một glucozit gọi là $lonixerin$ có cấu tạo $luteolin-7-rhamnoza$.",
          "Qua thực nghiệm chúng tôi thấy trong kim ngân có nhiều $saponozit$ (Đỗ Tất Lợi)."
        ],
        "cach_dung_bao_che": "Kim ngân có thể trồng ở miền núi cũng như ở đồng bằng. Đất đai và khí hậu Hà Nội cũng rất thích hợp. Ta có thể trồng bằng dâm cành: cắt những cành bánh tẻ dài chừng $20-60cm$, khoanh thành khoanh, chôn xuống dưới đất, để chừa đoạn sau cùng; vào thời kỳ đầu cần tưới đều. Có thể trồng quanh năm nhưng tốt nhất vào tháng 9-10 hoặc tháng 2-3. Sau một năm có thể bắt đầu thu hoạch; thu hoạch lâu năm, càng về những năm sau càng nhiều hoa. Nếu hái hoa cần hái vào lúc hoa sắp nở hay khi hoa mới nở, màu còn trắng chưa chuyển vàng. Có thể hái hoa riêng, cành lá riêng nhưng có thể hái hoa kèm theo một ít cành lá, về nhà mới phân, chia cành lá riêng, hoa riêng. Hoa hay cành lá hái về phơi hay sấy khô là dùng được. Không phải chế biến gì khác. Việc bảo quản hoa và cành lá kim ngân tương đối dễ vì ít bị mốc mọt."
      },
      "confidence_score": 0.95
    }
  ],
  "relationships": [
    {
      "from": "VI_THUOC_KIM_NGAN",
      "to": "V_NGOT",
      "relation_type": "CO_VI",
      "properties": {
        "mo_ta_chi_tiet": "Kim ngân vị ngọt"
      },
      "source": {
        "source_id": "CT_VT_VN_T90",
        "all_sources": [
          "CT_VT_VN_T90"
        ]
      },
      "confidence_score": 0.75
    },
    {
      "from": "VI_THUOC_KIM_NGAN",
      "to": "T_HAN",
      "relation_type": "CO_TINH",
      "properties": {
        "mo_ta_chi_tiet": "Kim ngân tính hàn (lạnh)"
      },
      "source": {
        "source_id": "CT_VT_VN_T90",
        "all_sources": [
          "CT_VT_VN_T90"
        ]
      },
      "confidence_score": 0.75
    },
    {
      "from": "VI_THUOC_KIM_NGAN",
      "to": "K_PHE",
      "relation_type": "QUY_KINH",
      "properties": {
        "mo_ta_chi_tiet": "Kim ngân vào kinh phế"
      },
      "source": {
        "source_id": "CT_VT_VN_T90",
        "all_sources": [
          "CT_VT_VN_T90"
        ]
      },
      "confidence_score": 0.75
    },
    {
      "from": "VI_THUOC_KIM_NGAN",
      "to": "K_VI",
      "relation_type": "QUY_KINH",
      "properties": {
        "mo_ta_chi_tiet": "Kim ngân vào kinh vị"
      },
      "source": {
        "source_id": "CT_VT_VN_T90",
        "all_sources": [
          "CT_VT_VN_T90"
        ]
      },
      "confidence_score": 0.75
    },
    {
      "from": "VI_THUOC_KIM_NGAN",
      "to": "K_TAM",
      "relation_type": "QUY_KINH",
      "properties": {
        "mo_ta_chi_tiet": "Kim ngân vào kinh tâm"
      },
      "source": {
        "source_id": "CT_VT_VN_T90",
        "all_sources": [
          "CT_VT_VN_T90"
        ]
      },
      "confidence_score": 0.75
    },
    {
      "from": "VI_THUOC_KIM_NGAN",
      "to": "K_TY",
      "relation_type": "QUY_KINH",
      "properties": {
        "mo_ta_chi_tiet": "Kim ngân vào kinh tỳ"
      },
      "source": {
        "source_id": "CT_VT_VN_T90",
        "all_sources": [
          "CT_VT_VN_T90"
        ]
      },
      "confidence_score": 0.75
    },
    {
      "from": "VI_THUOC_KIM_NGAN",
      "to": "HC_INOZIT",
      "relation_type": "CO_CHUA_HOAT_CHAT",
      "properties": {
        "mo_ta_chi_tiet": "Theo Tăng Quảng Phương, trong hoa kim ngân có $inozit$ (hay $inozitol$) chừng $1\\%$.",
        "ghi_chu": "Không có thông tin"
      },
      "source": {
        "source_id": "CT_VT_VN_T90",
        "all_sources": [
          "CT_VT_VN_T90"
        ]
      },
      "confidence_score": 0.75
    },
    {
      "from": "VI_THUOC_KIM_NGAN",
      "to": "HC_LONIXERIN",
      "relation_type": "CO_CHUA_HOAT_CHAT",
      "properties": {
        "mo_ta_chi_tiet": "Năm 1961, một số nhà nghiên cứu Nhật Bản cho biết trong kim ngân có một glucozit gọi là $lonixerin$ có cấu tạo $luteolin-7-rhamnoza$.",
        "ghi_chu": "Không có thông tin"
      },
      "source": {
        "source_id": "CT_VT_VN_T90",
        "all_sources": [
          "CT_VT_VN_T90"
        ]
      },
      "confidence_score": 0.75
    },
    {
      "from": "VI_THUOC_KIM_NGAN",
      "to": "HC_SAPONOZIT",
      "relation_type": "CO_CHUA_HOAT_CHAT",
      "properties": {
        "mo_ta_chi_tiet": "Qua thực nghiệm chúng tôi thấy trong kim ngân có nhiều $saponozit$ (Đỗ Tất Lợi).",
        "ghi_chu": "Không có thông tin"
      },
      "source": {
        "source_id": "CT_VT_VN_T90",
        "all_sources": [
          "CT_VT_VN_T90"
        ]
      },
      "confidence_score": 0.75
    },
    {
      "from": "VI_THUOC_KIM_NGAN",
      "to": "B_MUN_NHOT",
      "relation_type": "CHU_TRI_BENH",
      "properties": {
        "lieu_luong": "Tham khảo liều dùng chung của vị thuốc",
        "cach_dung": "Pha nước uống thay nước chè | Chỉ định lâm sàng theo kinh nghiệm",
        "ghi_chu": "CT_VT_VN_T92"
      },
      "source": {
        "source_id": "CT_VT_VN_T90",
        "all_sources": [
          "CT_VT_VN_T90"
        ]
      },
      "confidence_score": 0.75
    },
    {
      "from": "VI_THUOC_KIM_NGAN",
      "to": "B_ROM_SAY",
      "relation_type": "CHU_TRI_BENH",
      "properties": {
        "lieu_luong": "Tham khảo liều dùng chung của vị thuốc",
        "cach_dung": "Pha nước uống thay nước chè",
        "ghi_chu": "CT_VT_VN_T92"
      },
      "source": {
        "source_id": "CT_VT_VN_T90",
        "all_sources": [
          "CT_VT_VN_T90"
        ]
      },
      "confidence_score": 0.75
    },
    {
      "from": "VI_THUOC_KIM_NGAN",
      "to": "B_LEN_DAU",
      "relation_type": "CHU_TRI_BENH",
      "properties": {
        "lieu_luong": "Tham khảo liều dùng chung của vị thuốc",
        "cach_dung": "Pha nước uống thay nước chè",
        "ghi_chu": "CT_VT_VN_T92"
      },
      "source": {
        "source_id": "CT_VT_VN_T90",
        "all_sources": [
          "CT_VT_VN_T90"
        ]
      },
      "confidence_score": 0.75
    },
    {
      "from": "VI_THUOC_KIM_NGAN",
      "to": "B_LEN_SOI",
      "relation_type": "CHU_TRI_BENH",
      "properties": {
        "lieu_luong": "Tham khảo liều dùng chung của vị thuốc",
        "cach_dung": "Pha nước uống thay nước chè",
        "ghi_chu": "CT_VT_VN_T92"
      },
      "source": {
        "source_id": "CT_VT_VN_T90",
        "all_sources": [
          "CT_VT_VN_T90"
        ]
      },
      "confidence_score": 0.75
    },
    {
      "from": "VI_THUOC_KIM_NGAN",
      "to": "CN_TA_LY",
      "relation_type": "CO_CONG_NANG",
      "properties": {
        "lieu_luong": "Tham khảo liều dùng chung của vị thuốc",
        "cach_dung": "Pha nước uống thay nước chè | Chỉ định lâm sàng theo kinh nghiệm",
        "ghi_chu": "CT_VT_VN_T92"
      },
      "source": {
        "source_id": "CT_VT_VN_T90",
        "all_sources": [
          "CT_VT_VN_T90"
        ]
      },
      "confidence_score": 0.75
    },
    {
      "from": "VI_THUOC_KIM_NGAN",
      "to": "CN_GIANG_MAI",
      "relation_type": "CO_CONG_NANG",
      "properties": {
        "lieu_luong": "Tham khảo liều dùng chung của vị thuốc",
        "cach_dung": "Pha nước uống thay nước chè | Chỉ định lâm sàng theo kinh nghiệm",
        "ghi_chu": "CT_VT_VN_T92"
      },
      "source": {
        "source_id": "CT_VT_VN_T90",
        "all_sources": [
          "CT_VT_VN_T90"
        ]
      },
      "confidence_score": 0.75
    },
    {
      "from": "VI_THUOC_KIM_NGAN",
      "to": "B_SOT",
      "relation_type": "CHU_TRI_BENH",
      "properties": {
        "lieu_luong": "Tham khảo liều dùng chung của vị thuốc",
        "cach_dung": "Chỉ định lâm sàng theo kinh nghiệm",
        "ghi_chu": "CT_VT_VN_T92"
      },
      "source": {
        "source_id": "CT_VT_VN_T90",
        "all_sources": [
          "CT_VT_VN_T90"
        ]
      },
      "confidence_score": 0.75
    },
    {
      "from": "VI_THUOC_KIM_NGAN",
      "to": "B_MAN_NGUA",
      "relation_type": "CHU_TRI_BENH",
      "properties": {
        "lieu_luong": "Tham khảo liều dùng chung của vị thuốc",
        "cach_dung": "Chỉ định lâm sàng theo kinh nghiệm",
        "ghi_chu": "CT_VT_VN_T92"
      },
      "source": {
        "source_id": "CT_VT_VN_T90",
        "all_sources": [
          "CT_VT_VN_T90"
        ]
      },
      "confidence_score": 0.75
    },
    {
      "from": "VI_THUOC_KIM_NGAN",
      "to": "B_SOT_NONG",
      "relation_type": "CHU_TRI_BENH",
      "properties": {
        "lieu_luong": "Tham khảo liều dùng chung của vị thuốc",
        "cach_dung": "Chỉ định lâm sàng theo kinh nghiệm",
        "ghi_chu": "CT_VT_VN_T92"
      },
      "source": {
        "source_id": "CT_VT_VN_T90",
        "all_sources": [
          "CT_VT_VN_T90"
        ]
      },
      "confidence_score": 0.75
    },
    {
      "from": "VI_THUOC_KIM_NGAN",
      "to": "B_SOT_RET",
      "relation_type": "CHU_TRI_BENH",
      "properties": {
        "lieu_luong": "Tham khảo liều dùng chung của vị thuốc",
        "cach_dung": "Chỉ định lâm sàng theo kinh nghiệm",
        "ghi_chu": "CT_VT_VN_T92"
      },
      "source": {
        "source_id": "CT_VT_VN_T90",
        "all_sources": [
          "CT_VT_VN_T90"
        ]
      },
      "confidence_score": 0.75
    },
    {
      "from": "VI_THUOC_KIM_NGAN",
      "to": "B_VIEM_MUI_DI_UNG",
      "relation_type": "CHU_TRI_BENH",
      "properties": {
        "lieu_luong": "Tham khảo liều dùng chung của vị thuốc",
        "cach_dung": "Chỉ định lâm sàng theo kinh nghiệm",
        "ghi_chu": "CT_VT_VN_T92"
      },
      "source": {
        "source_id": "CT_VT_VN_T90",
        "all_sources": [
          "CT_VT_VN_T90"
        ]
      },
      "confidence_score": 0.75
    },
    {
      "from": "VI_THUOC_KIM_NGAN",
      "to": "B_THAP_KHOP",
      "relation_type": "CHU_TRI_BENH",
      "properties": {
        "lieu_luong": "Tham khảo liều dùng chung của vị thuốc",
        "cach_dung": "Chỉ định lâm sàng theo kinh nghiệm",
        "ghi_chu": "CT_VT_VN_T92"
      },
      "source": {
        "source_id": "CT_VT_VN_T90",
        "all_sources": [
          "CT_VT_VN_T90"
        ]
      },
      "confidence_score": 0.75
    },
    {
      "from": "VI_THUOC_KIM_NGAN",
      "to": "B_DI_UNG",
      "relation_type": "CHU_TRI_BENH",
      "properties": {
        "lieu_luong": "Tham khảo liều dùng chung của vị thuốc",
        "cach_dung": "Chỉ định lâm sàng theo kinh nghiệm",
        "ghi_chu": "CT_VT_VN_T92"
      },
      "source": {
        "source_id": "CT_VT_VN_T90",
        "all_sources": [
          "CT_VT_VN_T90"
        ]
      },
      "confidence_score": 0.75
    },
    {
      "from": "BT_THONG_TIEU_KIM_NGAN",
      "to": "VI_THUOC_KIM_NGAN",
      "relation_type": "BAO_GOM_VI_THUOC",
      "properties": {
        "lieu_luong": "$6g$ (nếu là hoa) hoặc $12g$",
        "vai_tro": "Quân",
        "ghi_chu": "CT_VT_VN_T92"
      },
      "source": {
        "source_id": "CT_VT_VN_T90",
        "all_sources": [
          "CT_VT_VN_T90"
        ]
      },
      "confidence_score": 0.75
    },
    {
      "from": "BT_THONG_TIEU_KIM_NGAN",
      "to": "B_MUN_NHOT",
      "relation_type": "CHU_TRI_BENH",
      "properties": {
        "lieu_luong": "2 đến 4 liều/ngày (người lớn); 1 đến 2 liều/ngày (trẻ em) | Chia 2 hay 3 lần uống trong ngày",
        "cach_dung": "Sắc còn $10ml$, thêm đường vào cho đủ ngọt (chừng $4g$). Đóng vào ống hàn kín, hấp tiệt trùng để bảo quản. Nếu dùng ngay thì không cần đóng ống và chỉ cần đun sôi rồi giữ sôi trong 15 phút đến nửa giờ là uống được. | Sắc còn $100ml$",
        "ghi_chu": "CT_VT_VN_T92"
      },
      "source": {
        "source_id": "CT_VT_VN_T90",
        "all_sources": [
          "CT_VT_VN_T90"
        ]
      },
      "confidence_score": 0.75
    },
    {
      "from": "BT_THONG_TIEU_KIM_NGAN",
      "to": "B_MAN_NGUA",
      "relation_type": "CHU_TRI_BENH",
      "properties": {
        "lieu_luong": "2 đến 4 liều/ngày (người lớn); 1 đến 2 liều/ngày (trẻ em) | Chia 2 hay 3 lần uống trong ngày",
        "cach_dung": "Sắc còn $10ml$, thêm đường vào cho đủ ngọt (chừng $4g$). Đóng vào ống hàn kín, hấp tiệt trùng để bảo quản. Nếu dùng ngay thì không cần đóng ống và chỉ cần đun sôi rồi giữ sôi trong 15 phút đến nửa giờ là uống được. | Sắc còn $100ml$",
        "ghi_chu": "CT_VT_VN_T92"
      },
      "source": {
        "source_id": "CT_VT_VN_T90",
        "all_sources": [
          "CT_VT_VN_T90"
        ]
      },
      "confidence_score": 0.75
    },
    {
      "from": "BT_THONG_TIEU_KIM_NGAN",
      "to": "B_DI_UNG",
      "relation_type": "CHU_TRI_BENH",
      "properties": {
        "lieu_luong": "2 đến 4 liều/ngày (người lớn); 1 đến 2 liều/ngày (trẻ em)",
        "cach_dung": "Sắc còn $10ml$, thêm đường vào cho đủ ngọt (chừng $4g$). Đóng vào ống hàn kín, hấp tiệt trùng để bảo quản. Nếu dùng ngay thì không cần đóng ống và chỉ cần đun sôi rồi giữ sôi trong 15 phút đến nửa giờ là uống được.",
        "ghi_chu": "CT_VT_VN_T92"
      },
      "source": {
        "source_id": "CT_VT_VN_T90",
        "all_sources": [
          "CT_VT_VN_T90"
        ]
      },
      "confidence_score": 0.75
    },
    {
      "from": "BT_THONG_TIEU_KIM_NGAN",
      "to": "VI_THUOC_KE_DAU_NGUA",
      "relation_type": "BAO_GOM_VI_THUOC",
      "properties": {
        "lieu_luong": "$3g$",
        "vai_tro": "Tá",
        "ghi_chu": "CT_VT_VN_T92"
      },
      "source": {
        "source_id": "CT_VT_VN_T90",
        "all_sources": [
          "CT_VT_VN_T90"
        ]
      },
      "confidence_score": 0.75
    },
    {
      "from": "BT_THONG_TIEU_KIM_NGAN",
      "to": "VI_THUOC_CAM_THAO",
      "relation_type": "BAO_GOM_VI_THUOC",
      "properties": {
        "lieu_luong": "$3g$",
        "vai_tro": "Tá",
        "ghi_chu": "CT_VT_VN_T92"
      },
      "source": {
        "source_id": "CT_VT_VN_T90",
        "all_sources": [
          "CT_VT_VN_T90"
        ]
      },
      "confidence_score": 0.75
    },
    {
      "from": "BT_THONG_TIEU_KIM_NGAN",
      "to": "CN_THONG_TIEU",
      "relation_type": "CO_CONG_NANG",
      "properties": {
        "lieu_luong": "Chia 2 hay 3 lần uống trong ngày",
        "cach_dung": "Sắc còn $100ml$",
        "ghi_chu": "CT_VT_VN_T92"
      },
      "source": {
        "source_id": "CT_VT_VN_T90",
        "all_sources": [
          "CT_VT_VN_T90"
        ]
      },
      "confidence_score": 0.75
    },
    {
      "from": "BT_CAM_KIEU_TAN",
      "to": "VI_THUOC_KIM_NGAN",
      "relation_type": "BAO_GOM_VI_THUOC",
      "properties": {
        "lieu_luong": "$40g$",
        "vai_tro": "Quân",
        "ghi_chu": "CT_VT_VN_T92"
      },
      "source": {
        "source_id": "CT_VT_VN_T90",
        "all_sources": [
          "CT_VT_VN_T90"
        ]
      },
      "confidence_score": 0.75
    },
    {
      "from": "BT_CAM_KIEU_TAN",
      "to": "VI_THUOC_LIEN_KIEU",
      "relation_type": "BAO_GOM_VI_THUOC",
      "properties": {
        "lieu_luong": "$40g$",
        "vai_tro": "Quân",
        "ghi_chu": "CT_VT_VN_T92"
      },
      "source": {
        "source_id": "CT_VT_VN_T90",
        "all_sources": [
          "CT_VT_VN_T90"
        ]
      },
      "confidence_score": 0.75
    },
    {
      "from": "BT_CAM_KIEU_TAN",
      "to": "VI_THUOC_KINH_GIOI_TUE",
      "relation_type": "BAO_GOM_VI_THUOC",
      "properties": {
        "lieu_luong": "$16g$",
        "vai_tro": "Tá",
        "ghi_chu": "CT_VT_VN_T92"
      },
      "source": {
        "source_id": "CT_VT_VN_T90",
        "all_sources": [
          "CT_VT_VN_T90"
        ]
      },
      "confidence_score": 0.75
    },
    {
      "from": "BT_CAM_KIEU_TAN",
      "to": "VI_THUOC_CAT_CANH",
      "relation_type": "BAO_GOM_VI_THUOC",
      "properties": {
        "lieu_luong": "$24g$",
        "vai_tro": "Tá",
        "ghi_chu": "CT_VT_VN_T92"
      },
      "source": {
        "source_id": "CT_VT_VN_T90",
        "all_sources": [
          "CT_VT_VN_T90"
        ]
      },
      "confidence_score": 0.75
    },
    {
      "from": "BT_CAM_KIEU_TAN",
      "to": "VI_THUOC_DAM_DAU_SI",
      "relation_type": "BAO_GOM_VI_THUOC",
      "properties": {
        "lieu_luong": "$20g$",
        "vai_tro": "Tá",
        "ghi_chu": "CT_VT_VN_T92"
      },
      "source": {
        "source_id": "CT_VT_VN_T90",
        "all_sources": [
          "CT_VT_VN_T90"
        ]
      },
      "confidence_score": 0.75
    },
    {
      "from": "BT_CAM_KIEU_TAN",
      "to": "VI_THUOC_BAC_HA",
      "relation_type": "BAO_GOM_VI_THUOC",
      "properties": {
        "lieu_luong": "$24g$",
        "vai_tro": "Tá",
        "ghi_chu": "CT_VT_VN_T92"
      },
      "source": {
        "source_id": "CT_VT_VN_T90",
        "all_sources": [
          "CT_VT_VN_T90"
        ]
      },
      "confidence_score": 0.75
    },
    {
      "from": "BT_CAM_KIEU_TAN",
      "to": "VI_THUOC_NGUU_BANG_TU",
      "relation_type": "BAO_GOM_VI_THUOC",
      "properties": {
        "lieu_luong": "$24g$",
        "vai_tro": "Tá",
        "ghi_chu": "CT_VT_VN_T92"
      },
      "source": {
        "source_id": "CT_VT_VN_T90",
        "all_sources": [
          "CT_VT_VN_T90"
        ]
      },
      "confidence_score": 0.75
    },
    {
      "from": "BT_CAM_KIEU_TAN",
      "to": "VI_THUOC_DAM_TRUC_DIEP",
      "relation_type": "BAO_GOM_VI_THUOC",
      "properties": {
        "lieu_luong": "$16g$",
        "vai_tro": "Tá",
        "ghi_chu": "CT_VT_VN_T92"
      },
      "source": {
        "source_id": "CT_VT_VN_T90",
        "all_sources": [
          "CT_VT_VN_T90"
        ]
      },
      "confidence_score": 0.75
    },
    {
      "from": "BT_CAM_KIEU_TAN",
      "to": "B_MUN_NHOT",
      "relation_type": "CHU_TRI_BENH",
      "properties": {
        "lieu_luong": "Ngày uống 1-2 lần, mỗi lần uống $12g$ bột",
        "cach_dung": "Tất cả sấy khô tán bột. Có thể làm thành viên.",
        "ghi_chu": "CT_VT_VN_T92"
      },
      "source": {
        "source_id": "CT_VT_VN_T90",
        "all_sources": [
          "CT_VT_VN_T90"
        ]
      },
      "confidence_score": 0.75
    },
    {
      "from": "BT_CAM_KIEU_TAN",
      "to": "B_SOT",
      "relation_type": "CHU_TRI_BENH",
      "properties": {
        "lieu_luong": "Ngày uống 1-2 lần, mỗi lần uống $12g$ bột",
        "cach_dung": "Tất cả sấy khô tán bột. Có thể làm thành viên.",
        "ghi_chu": "CT_VT_VN_T92"
      },
      "source": {
        "source_id": "CT_VT_VN_T90",
        "all_sources": [
          "CT_VT_VN_T90"
        ]
      },
      "confidence_score": 0.75
    },
    {
      "from": "BT_CAM_KIEU_TAN",
      "to": "B_NGOT",
      "relation_type": "CHU_TRI_BENH",
      "properties": {
        "lieu_luong": "Ngày uống 1-2 lần, mỗi lần uống $12g$ bột",
        "cach_dung": "Tất cả sấy khô tán bột. Có thể làm thành viên.",
        "ghi_chu": "CT_VT_VN_T92"
      },
      "source": {
        "source_id": "CT_VT_VN_T90",
        "all_sources": [
          "CT_VT_VN_T90"
        ]
      },
      "confidence_score": 0.75
    },
    {
      "from": "VI_THUOC_KIM_NGAN",
      "to": "CN_THANH_NHIET_GIAI_DOC",
      "relation_type": "CO_CONG_NANG",
      "properties": {
        "mo_ta_chi_tiet": "Thanh nhiệt giải độc, dùng chữa sốt, mụn nhọt, tả lỵ, giang mai."
      },
      "source": {
        "source_id": "CT_VT_VN_T90",
        "all_sources": [
          "CT_VT_VN_T90"
        ]
      },
      "confidence_score": 0.75
    },
    {
      "from": "VI_THUOC_KIM_NGAN",
      "to": "CN_DIEN_NIEN",
      "relation_type": "CO_CONG_NANG",
      "properties": {
        "mo_ta_chi_tiet": "Uống lâu nhẹ người tăng tuổi thọ."
      },
      "source": {
        "source_id": "CT_VT_VN_T90",
        "all_sources": [
          "CT_VT_VN_T90"
        ]
      },
      "confidence_score": 0.75
    },
    {
      "from": "VI_THUOC_KIM_NGAN",
      "to": "DL_KHANG_SINH",
      "relation_type": "CO_TAC_DUNG_DUOC_LY",
      "properties": {
        "mo_ta_chi_tiet": "Nước hoa kim ngân có tác dụng ức chế rất mạnh đối với tụ cầu khuẩn vi khuẩn thương hàn, trùng lỵ Shiga. Nước sắc có tác dụng mạnh hơn các dạng bào chế khác.",
        "ghi_chu": "Năm 1950, Lưu Quốc Thanh (Trung Hoa tân y học báo) đã báo cáo dùng nước sắc cô đặc 100$\\%$ của hoa kim ngân thấy có tác dụng kháng sinh rất mạnh đối với vi trùng thương hàn, tả, liên cầu khuẩn tiêu máu (vòng vô khuẩn tới $11-20mm$), vi trùng lỵ, trực khuẩn coli, tụ cầu khuẩn, phế cầu khuẩn, đối với bạch hầu cũng có tác dụng nhưng kém hơn ($2-10 mm$)."
      },
      "source": {
        "source_id": "CT_VT_VN_T90",
        "all_sources": [
          "CT_VT_VN_T90"
        ]
      },
      "confidence_score": 0.75
    },
    {
      "from": "VI_THUOC_KIM_NGAN",
      "to": "DL_KHANG_KHUAN",
      "relation_type": "CO_TAC_DUNG_DUOC_LY",
      "properties": {
        "mo_ta_chi_tiet": "Nồng độ loãng nhất có tác dụng ức chế đối với sự phát triển của vi trùng:nVi trùng ly Shiga 1/640nVi trùng lỵ Flexner 1/2560n- Sonnei 1/1280n- Thương hàn 1/320nVi trùng phó thương hàn A 1/300n- phó thương hàn B 1/300n- tả 1/300n- trực khuẩn coli 1/160n- dịch hạch 1/160nTụ cầu khuẩn vàng (aureus) 1/1280nLiên cầu khuẩn tiêu máu A 1/40nLiên cầu khuẩn tiêu máu B 1/320nBạch hầu 1/160nPhế cầu khuẩn 1/80 | Nước sắc lá kim ngân với nồng độ $20-1,2\\%$ có tác dụng ức chế vi trùng ly Shiga, nước sắc lá kim ngân với nồng độ $20-5\\%$ có tác dụng ức chế đối với vi trùng phó thương hàn A, nồng độ $100\\%$ có tác dụng đối với tụ cầu khuẩn, nhưng đặc biệt các tác giả nhận thấy nước sắc hoa kim ngân lại hoàn toàn không có tác dụng kháng sinh.",
        "ghi_chu": "Năm 1960, Sở nghiên cứu Trung y dược tỉnh Giang Tây Trung Quốc có nghiên cứu so sánh tác dụng kháng sinh của nước sắc hoa kim ngân và nước sắc lá kim ngân thì đã đi tới kết luận."
      },
      "source": {
        "source_id": "CT_VT_VN_T90",
        "all_sources": [
          "CT_VT_VN_T90"
        ]
      },
      "confidence_score": 0.75
    },
    {
      "from": "VI_THUOC_KIM_NGAN",
      "to": "DL_DUONG_HUYET",
      "relation_type": "CO_TAC_DUNG_DUOC_LY",
      "properties": {
        "mo_ta_chi_tiet": "Sau khi cho thỏ uống nước sắc hoa kim ngân thì lượng huyết đường tăng; hiện tượng này kéo dài $5-6$ giờ mới trở lại bình thường.",
        "ghi_chu": "Năm 1930, Mẫn Bính Kỳ (Dược lý đích sinh dược học, 1933) đã thông báo."
      },
      "source": {
        "source_id": "CT_VT_VN_T90",
        "all_sources": [
          "CT_VT_VN_T90"
        ]
      },
      "confidence_score": 0.75
    },
    {
      "from": "VI_THUOC_KIM_NGAN",
      "to": "DL_CHONG_CHOANG_PHAN_VE",
      "relation_type": "CO_TAC_DUNG_DUOC_LY",
      "properties": {
        "mo_ta_chi_tiet": "Nước sắc kim ngân có khả năng ngăn chặn choáng phản vệ trên chuột lang: Trên chuột lang được uống kim ngân, số lượng và chất lượng tế bào hạt (mastocytes) ở mạng treo ruột ít thay đổi, lượng histamin ở phổi chuột lang bị choáng phản vệ cao gấp rưỡi so với chuột lang bình thường hay đã được uống kim ngân trước khi gây choáng phản vệ.",
        "ghi_chu": "Năm 1966, Đỗ Tất Lợi, Nguyễn Năng An và Bùi Chí Hiếu (Hội nghị thuốc nam lần thứ 4, Hà Nội) đã báo cáo."
      },
      "source": {
        "source_id": "CT_VT_VN_T90",
        "all_sources": [
          "CT_VT_VN_T90"
        ]
      },
      "confidence_score": 0.75
    },
    {
      "from": "VI_THUOC_KIM_NGAN",
      "to": "DL_DOC_TINH",
      "relation_type": "CO_TAC_DUNG_DUOC_LY",
      "properties": {
        "mo_ta_chi_tiet": "Chuột nhắt trắng uống liên tục 7 ngày với liều gấp 150 lần điều trị cho người, chuột vẫn sống bình thường, giải phẫu các bộ phận không thay đổi gì đặc biệt."
      },
      "source": {
        "source_id": "CT_VT_VN_T90",
        "all_sources": [
          "CT_VT_VN_T90"
        ]
      },
      "confidence_score": 0.75
    }
  ],
  "metadata": {
    "scientific_metrics": {
      "data_richness_index": 79.0,
      "reliability_c_score": 0.7542,
      "total_confidence_sum": 36.2
    },
    "validator_pass_score": 100,
    "processed_at": "2026-04-19 08:41:55"
  }
}